{
  "topLinks": [
    { "label": "수행평가 캘린더 샘플", "url": "https://perf-calendar-prototype.vercel.app/" },
    { "label": "문제로 연습하기(처음 로딩 시 몇 초 기다려야 합니다)", "url": "/testlab/" }
  ],
  "subjects": [
    { "name": "국어", "documents": [
      { "title": "1-1 기말 국어 문법(누적 범위)", "url": "https://raw.githubusercontent.com/HANSIU-cmd/exam-site/main/files/1-1 기말 국어 문법(누적 범위).pdf" },
      { "title": "1-1 기말 국어 중간범위 복습용", "url": "https://raw.githubusercontent.com/HANSIU-cmd/exam-site/main/files/1-1 기말 국어 중간범위 복습용.pdf" },
      { "title": "1-1 기말 국어 중간범위 복습용 (삼성노트)", "url": "https://raw.githubusercontent.com/HANSIU-cmd/exam-site/main/files/1-1 기말 국어 중간범위 복습용.sdocx" }
    ]},
    { "name": "영어", "documents": [
      { "title": "1-1 기말 영어 올림포스+교과서+6모 지문-해석", "url": "https://raw.githubusercontent.com/HANSIU-cmd/exam-site/main/files/1-1 기말 영어 올림포스+교과서+6모 지문-해석.pdf" },
      { "title": "1-1 기말 영어 변형문제(6모)", "url": "https://raw.githubusercontent.com/HANSIU-cmd/exam-site/main/files/1-1 기말 영어 변형문제(6모).pdf" },
      { "title": "1-1 기말 영어 변형문제(교과서 3, 4과)", "url": "https://raw.githubusercontent.com/HANSIU-cmd/exam-site/main/files/1-1 기말 영어 변형문제(교과서 3, 4과).pdf" },
      { "title": "1-1 기말 영어 변형문제(올림포스)", "url": "https://raw.githubusercontent.com/HANSIU-cmd/exam-site/main/files/1-1 기말 영어 변형문제(올림포스).pdf" },
      { "title": "1-1 기말 영어 모의시험(6모)", "url": "https://raw.githubusercontent.com/HANSIU-cmd/exam-site/main/files/1-1 기말 영어 모의시험(6모).pdf" },
      { "title": "1-1 기말 영어 모의시험(올림포스)", "url": "https://raw.githubusercontent.com/HANSIU-cmd/exam-site/main/files/1-1 기말 영어 모의시험(올림포스).pdf" }
    ]},
    { "name": "수학", "documents": [
      { "title": "1-1 기말 수학 어려운 문제 모음", "url": "https://raw.githubusercontent.com/HANSIU-cmd/exam-site/main/files/1-1 기말 수학 어려운 문제 모음.pdf" },
      { "title": "1-1 기말 수학 조합 공식", "url": "https://raw.githubusercontent.com/HANSIU-cmd/exam-site/main/files/1-1 기말 수학 조합 공식.pdf" }
    ]},
    { "name": "과학", "documents": [
      { "title": "1-1 기말 과학 요약정리+교과서", "url": "https://raw.githubusercontent.com/HANSIU-cmd/exam-site/main/files/1-1 기말 과학 요약정리+교과서.pdf" },
      { "title": "1-1 기말 과학 연습문제 참고(2023 9모)", "url": "https://raw.githubusercontent.com/HANSIU-cmd/exam-site/main/files/1-1 기말 과학 연습문제 참고(2023 9모).pdf" },
      { "title": "2023 9모 과학 정답", "url": "https://raw.githubusercontent.com/HANSIU-cmd/exam-site/main/files/2023 9모 과학 정답.pdf" },
      { "title": "1-1 기말 과학 연습문제 참고(2024 9모)", "url": "https://raw.githubusercontent.com/HANSIU-cmd/exam-site/main/files/1-1 기말 과학 연습문제 참고(2024 9모).pdf" },
      { "title": "2024 9모 과학 정답", "url": "https://raw.githubusercontent.com/HANSIU-cmd/exam-site/main/files/2024 9모 과학 정답.pdf" },
      { "title": "1-1 기말 과학 연습문제 참고(2025 9모)", "url": "https://raw.githubusercontent.com/HANSIU-cmd/exam-site/main/files/1-1 기말 과학 연습문제 참고(2025 9모).pdf" },
      { "title": "2025 9모 과학 정답", "url": "https://raw.githubusercontent.com/HANSIU-cmd/exam-site/main/files/2025 9모 과학 정답.pdf" }
    ]},
    { "name": "사회", "documents": [
      { "title": "1-1 기말 사회 요약정리", "url": "https://raw.githubusercontent.com/HANSIU-cmd/exam-site/main/files/1-1 기말 사회 요약정리.pdf" },
      { "title": "1-1 기말 사회 요약정리+교과서 스캔", "url": "https://raw.githubusercontent.com/HANSIU-cmd/exam-site/main/files/1-1 기말 사회 요약정리+교과서 스캔.pdf" }
    ]},
    { "name": "한국사", "documents": [
      { "title": "1-1 기말 한국사 요약정리", "url": "https://raw.githubusercontent.com/HANSIU-cmd/exam-site/main/files/1-1 기말 한국사 요약정리.pdf" },
      { "title": "1-1 기말 한국사 요약정리+교과서 스캔", "url": "https://raw.githubusercontent.com/HANSIU-cmd/exam-site/main/files/1-1 기말 한국사 요약정리+교과서 스캔.pdf" },
      { "title": "1-1 기말 한국사 문화 표", "url": "https://raw.githubusercontent.com/HANSIU-cmd/exam-site/main/files/1-1 기말 한국사 문화 표.pdf" }
    ]},
    { "name": "한문", "documents": [
      { "title": "1-1 기말 한문 한자+한자어+성어+문장", "url": "https://raw.githubusercontent.com/HANSIU-cmd/exam-site/main/files/1-1 기말 한문 한자+한자어+성어+문장.pdf" }
    ]}
  ]
}
